horimote/__init__.py
horimote/client.py
horimote/exceptions.py
horimote/keys.py
horimote-0.4.1.dist-info/LICENSE
horimote-0.4.1.dist-info/METADATA
horimote-0.4.1.dist-info/WHEEL
horimote-0.4.1.dist-info/top_level.txt
horimote-0.4.1.dist-info/RECORD
