Metadata-Version: 2.1
Name: horimote
Version: 0.4.1
Summary: Async API wrapper for Samsumgs set-top boxes SMT-G7400 and SMT-G7401.
Home-page: https://github.com/benleb/horimote
Author: Ben Lebherz & Auke Willem Oosterhoff
Author-email: git@benleb.de
License: MIT
Platform: UNKNOWN
Classifier: Intended Audience :: Developers
Classifier: Operating System :: OS Independent
Classifier: Programming Language :: Python
Classifier: Programming Language :: Python :: 3.6
Classifier: Programming Language :: Python :: 3.7
Classifier: Topic :: Software Development :: Libraries :: Python Modules
Classifier: Topic :: Multimedia
